aria2_rpc/Aria2.py
aria2_rpc/__init__.py
aria2_json_rpc-0.0.3.dist-info/LICENSE
aria2_json_rpc-0.0.3.dist-info/METADATA
aria2_json_rpc-0.0.3.dist-info/WHEEL
aria2_json_rpc-0.0.3.dist-info/top_level.txt
aria2_json_rpc-0.0.3.dist-info/RECORD
