Metadata-Version: 2.1
Name: aria2-json-rpc
Version: 0.0.3
Summary: a naive aria2c rpc api lib
Home-page: https://github.com/Virace/aria2-rpc
Author: Virace
Author-email: Virace@yeah.net
License: UNKNOWN
Platform: UNKNOWN
Classifier: Programming Language :: Python :: 3
Classifier: License :: OSI Approved :: MIT License
Classifier: Operating System :: OS Independent
